<?xml version="1.0" encoding="utf-8"?>
<class id="cc856731-e882-43be-b1ee-0f36f34aeadb" type="Folder" typeId="3407a825-1331-4f3f-89a4-901903ed97ce">
  <name>modelers</name>
  <display>modelers</display>
  <isAbstract>false</isAbstract>
  <genericTypes />
  <isMapped>false</isMapped>
  <parentFolderId>bdb62872-0ea1-4c15-829b-2d123847d35b</parentFolderId>
  <stereotypes />
  <metadata />
  <childElements>
    <childElement id="b940f1de-beb5-4555-b53d-1b1605b5b7ff" type="Template Output" typeId="d421c322-7a51-4094-89fa-e5d8a0a97b27">
      <name>Intent.ModuleBuilder.DesignerConfig</name>
      <display>Intent.ModuleBuilder.DesignerConfig</display>
      <externalReference>Intent.ModuleBuilder</externalReference>
      <isAbstract>false</isAbstract>
      <genericTypes />
      <isMapped>false</isMapped>
      <parentFolderId>cc856731-e882-43be-b1ee-0f36f34aeadb</parentFolderId>
      <stereotypes />
      <metadata>
        <entry key="status" value="assigned" />
      </metadata>
      <childElements />
    </childElement>
    <childElement id="8dccb0c3-9602-4727-95af-3bd116e5ed7c" type="Template Output" typeId="d421c322-7a51-4094-89fa-e5d8a0a97b27">
      <name>Intent.ModuleBuilder.DesignerSettings</name>
      <display>Intent.ModuleBuilder.DesignerSettings</display>
      <externalReference>Intent.ModuleBuilder</externalReference>
      <isAbstract>false</isAbstract>
      <genericTypes />
      <isMapped>false</isMapped>
      <parentFolderId>cc856731-e882-43be-b1ee-0f36f34aeadb</parentFolderId>
      <stereotypes />
      <metadata>
        <entry key="status" value="assigned" />
      </metadata>
      <childElements />
    </childElement>
  </childElements>
</class>