<?xml version="1.0" encoding="utf-8"?>
<class id="a63f47e9-a0da-40b4-8b6a-08e362d172a1" type="Folder" typeId="3407a825-1331-4f3f-89a4-901903ed97ce">
  <name>Decorators</name>
  <display>Decorators</display>
  <isAbstract>false</isAbstract>
  <order>0</order>
  <genericTypes />
  <isMapped>false</isMapped>
  <parentFolderId>cc9a4c9e-686e-403b-84d7-00b3f54236e8</parentFolderId>
  <stereotypes />
  <childElements>
    <childElement id="76f14f98-f1f4-44b8-967c-c6da7fc9fd35" type="Template Output" typeId="d421c322-7a51-4094-89fa-e5d8a0a97b27">
      <name>Intent.ModuleBuilder.DecoratorTemplate</name>
      <display>Intent.ModuleBuilder.DecoratorTemplate</display>
      <externalReference>Intent.ModuleBuilder</externalReference>
      <isAbstract>false</isAbstract>
      <order>0</order>
      <genericTypes />
      <isMapped>false</isMapped>
      <parentFolderId>a63f47e9-a0da-40b4-8b6a-08e362d172a1</parentFolderId>
      <stereotypes />
      <childElements />
    </childElement>
    <childElement id="9574b227-a793-464b-af5f-8e7f711e30d2" type="Template Output" typeId="d421c322-7a51-4094-89fa-e5d8a0a97b27">
      <name>Intent.ModuleBuilder.DecoratorRegistration.Template</name>
      <display>Intent.ModuleBuilder.DecoratorRegistration.Template</display>
      <externalReference>Intent.ModuleBuilder</externalReference>
      <isAbstract>false</isAbstract>
      <order>0</order>
      <genericTypes />
      <isMapped>false</isMapped>
      <parentFolderId>a63f47e9-a0da-40b4-8b6a-08e362d172a1</parentFolderId>
      <stereotypes />
      <childElements />
    </childElement>
    <childElement id="3c637cf0-dd91-4fa5-973b-b79b3b9818e0" type="Template Output" typeId="d421c322-7a51-4094-89fa-e5d8a0a97b27">
      <name>Intent.ModuleBuilder.Templates.TemplateDecorator</name>
      <display>Intent.ModuleBuilder.Templates.TemplateDecorator</display>
      <externalReference>Intent.ModuleBuilder</externalReference>
      <isAbstract>false</isAbstract>
      <order>0</order>
      <genericTypes />
      <isMapped>false</isMapped>
      <parentFolderId>a63f47e9-a0da-40b4-8b6a-08e362d172a1</parentFolderId>
      <stereotypes />
      <childElements />
    </childElement>
    <childElement id="49177af9-83c7-4867-8aad-370c155a524d" type="Template Output" typeId="d421c322-7a51-4094-89fa-e5d8a0a97b27">
      <name>Intent.ModuleBuilder.Templates.TemplateDecoratorRegistration</name>
      <display>Intent.ModuleBuilder.Templates.TemplateDecoratorRegistration</display>
      <externalReference>Intent.ModuleBuilder</externalReference>
      <isAbstract>false</isAbstract>
      <order>0</order>
      <genericTypes />
      <isMapped>false</isMapped>
      <parentFolderId>a63f47e9-a0da-40b4-8b6a-08e362d172a1</parentFolderId>
      <stereotypes />
      <childElements />
    </childElement>
  </childElements>
</class>